fig_jam/__init__.py
fig_jam/loader/__init__.py
fig_jam/loader/_core.py
fig_jam/loader/_exceptions.py
fig_jam/loader/_messages.py
fig_jam/loader/_templates.py
fig_jam/parsers/__init__.py
fig_jam/parsers/_parsers.py
fig_jam/parsers/_parsers_errors.py
fig_jam/parsers/_parsers_utils.py
fig_jam/pipeline/__init__.py
fig_jam/pipeline/_model.py
fig_jam/pipeline/_validators.py
fig_jam/pipeline/discover_sources.py
fig_jam/pipeline/override_sources.py
fig_jam/pipeline/parse_sources.py
fig_jam/pipeline/validate_sources.py
fig_jam-0.1.0.dist-info/METADATA
fig_jam-0.1.0.dist-info/WHEEL
fig_jam-0.1.0.dist-info/licenses/LICENSE
fig_jam-0.1.0.dist-info/RECORD
